ptcr2/__init__.py
ptcr2/automata_utility.py
ptcr2/base_model.py
ptcr2/belief_tree.py
ptcr2/event_predictor.py
ptcr2/fom.py
ptcr2/markov_chain.py
ptcr2/markov_decision_process.py
ptcr-0.0.1.dist-info/LICENSE
ptcr-0.0.1.dist-info/METADATA
ptcr-0.0.1.dist-info/WHEEL
ptcr-0.0.1.dist-info/top_level.txt
ptcr-0.0.1.dist-info/RECORD
