Metadata-Version: 2.1
Name: ptcr
Version: 0.0.1
Summary: Construct and process PTCR simulations.
Author-email: Tiernan Lindauer <tiernanlind@tamu.edu>
Project-URL: Homepage, https://github.com/T-Lind/ptcr
Project-URL: Issues, https://github.com/T-Lind/ptcr/issues
Classifier: Programming Language :: Python :: 3
Classifier: License :: OSI Approved :: MIT License
Classifier: Operating System :: OS Independent
Requires-Python: ==3.9
License-File: LICENSE
